Metadata-Version: 2.1
Name: topsis-navneet-102003256
Version: 1.0.1
Summary: topsis implementation
Home-page: UNKNOWN
Author: Navneet Singh
Author-email: navneet1202@gmail.com
License: UNKNOWN
Platform: UNKNOWN
Classifier: Programming Language :: Python :: 3
Classifier: License :: OSI Approved :: MIT License
Classifier: Operating System :: OS Independent
Requires-Python: >=3.6
License-File: LICENSE.txt
